king/__init__.py
king-0.0.0.dist-info/METADATA
king-0.0.0.dist-info/RECORD
king-0.0.0.dist-info/WHEEL
king-0.0.0.dist-info/top_level.txt
